grpc_client/__init__.py
grpc_client/base_client.py
grpc_client/base_hook.py
grpc_client-0.0.2.dist-info/LICENSE
grpc_client-0.0.2.dist-info/METADATA
grpc_client-0.0.2.dist-info/WHEEL
grpc_client-0.0.2.dist-info/top_level.txt
grpc_client-0.0.2.dist-info/RECORD
