Metadata-Version: 2.1
Name: grpc-client
Version: 0.0.2
Summary: grpc client for python
Home-page: https://github.com/josephyin/grpc_client
Author: Joseph Yin
Author-email: josephyin@outlook.com
License: UNKNOWN
Platform: UNKNOWN
Classifier: Programming Language :: Python :: 3
Classifier: License :: OSI Approved :: MIT License
Classifier: Operating System :: OS Independent
Requires-Python: >=3.6
